{
  "video_id": "MWtbpypxca0",
  "title": "On Gravity - corrected version",
  "description": "This is the correct file that should have been uploaded - it has the audio to the first half - sorry for the earlier mistake - i was doing it at 2 in the morning!!",
  "published_at": "2015-05-17T17:48:06Z",
  "channel_id": "UC4AkVj-qnJxNtKuz3rkq16A",
  "channel_title": "Robert Murray-Smith",
  "tags": [
    "gravity",
    "energy"
  ],
  "duration": "PT14M22S",
  "view_count": "3420",
  "like_count": "129",
  "comment_count": "104",
  "url": "https://www.youtube.com/watch?v=MWtbpypxca0",
  "thumbnail": "https://i.ytimg.com/vi/MWtbpypxca0/hqdefault.jpg"
}