{
  "video_id": "2dDgUr7NpA4",
  "title": "How To Make Your Own Flux",
  "description": "Just  little aside on how to make a useful flux for yourself - many more things to make are on our 'make it' channel https://www.youtube.com/channel/UCVaUhDJTviZ17K8vXnR1HjQ/featured and materials for your own experiments at our webshop at www.workingink.co.uk.",
  "published_at": "2015-05-15T19:43:31Z",
  "channel_id": "UC4AkVj-qnJxNtKuz3rkq16A",
  "channel_title": "Robert Murray-Smith",
  "tags": [
    "flux",
    "soldering",
    "howto",
    "how to",
    "materials",
    "science",
    "chemistry",
    "robert",
    "murray-smoth",
    "fwg",
    "laboratory",
    "lab",
    "workshop",
    "solder",
    "equipment",
    "tools"
  ],
  "duration": "PT1M46S",
  "view_count": "225513",
  "like_count": "1997",
  "comment_count": "215",
  "url": "https://www.youtube.com/watch?v=2dDgUr7NpA4",
  "thumbnail": "https://i.ytimg.com/vi/2dDgUr7NpA4/hqdefault.jpg"
}