{
  "video_id": "wdzTSw8Y88Y",
  "title": "Man In A Shed - Episode 5",
  "description": "This video is an omnibus it includes;\n\n2191 Self Charging Solar Battery\n2192 MIT Breakthrough On Making All The Fresh Water We Need\n2193 Energy Farms - From Plant Power To Power Plant\n2194 Hydrogen On Demand - Improvements And A Possible Conspiracy\n2195 Bizarre Gears\n2196 The Spherical Coulisse Power Transfer Mechanism\n\nlinks\n\n2191 Self Charging Solar Battery\n\nyou can find the articles here:\nhttps://www.nature.com/articles/ncomms5921#Sec12\nhttps://www.sciencedirect.com/science/article/pii/S2352484723014798\n\n2192 MIT Breakthrough On Making All The Fresh Water We Need\n\nThe paper is here https://www.cell.com/joule/fulltext/S2542-4351(23)00360-4\nand it is open access\n\n2195 Bizarre Gears\n\nGzumwalt Cube Gear - https://www.youtube.com/watch?v=23ByThsWH2w&t=5s\nEmmett Lalish Heart Gear - https://www.youtube.com/watch?v=O-qwmRwOpFQ\nMankati Brain Gear - https://www.youtube.com/watch?v=0SV_UyZj2rA\nKiyoshi Adachi Nautilus Gears - https://www.youtube.com/watch?v=IUR-T4Nw-Sk\nBopp & Reuther Messtechnik GmbH Oval Gears - https://www.youtube.com/watch?v=mOpNVsVV4_w\nOskar Spherigear - https://www.youtube.com/watch?v=7Tv-aUC6lpM\nYamagata University ABENICS Gear - https://www.youtube.com/watch?v=hhDdfiRCQS4\nABENICS STL - https://www.thingiverse.com/thing:5788966\ntrinityscsp Mangle Rack - https://www.youtube.com/watch?v=W-j8U7xz3MY\nAkiyuki Brick Channel - https://www.youtube.com/watch?v=LbRijQcFI-4\nHenry Segerman Borromean hairpins - https://www.youtube.com/watch?v=WQ9ptuUxfk4\nHenry Segerman Donut Gears - https://www.youtube.com/watch?v=QhXjevOY_uk\n\n2195 Bizarre Gears\n\nYou can find the stl files here https://www.thingiverse.com/thing:6453237\nthese are the links for the credits \nNick's Steam Toys & More - https://www.youtube.com/@NickSteam8/videos\nthang010146 - https://www.youtube.com/watch?v=8OEczNJ7-U8",
  "published_at": "2024-02-19T15:17:28Z",
  "channel_id": "UC1E8OmOG17VckoPviOPmkMw",
  "channel_title": "TNT Omnibus",
  "tags": [
    "science",
    "comedy",
    "banter",
    "lab",
    "workshop",
    "laboratory",
    "diy",
    "d-i-y",
    "technology",
    "tech",
    "howto",
    "chemistry",
    "physics",
    "electronics"
  ],
  "duration": "PT45M7S",
  "view_count": "4925",
  "like_count": "258",
  "comment_count": "22",
  "url": "https://www.youtube.com/watch?v=wdzTSw8Y88Y",
  "thumbnail": "https://i.ytimg.com/vi/wdzTSw8Y88Y/hqdefault.jpg"
}