{
  "video_id": "GoqchqZfMCc",
  "title": "Conductive Ink For Electroplating Leaves",
  "description": "This ink is plating bath resistant and conductive to allow you to electroplate organic materials like cloth, leaves, wood, bone, etc.  I am always happy to have an e-mail at robertmurraysmith64@gmail.com if you feel like dropping me a line",
  "published_at": "2013-09-24T14:38:23Z",
  "channel_id": "UC4AkVj-qnJxNtKuz3rkq16A",
  "channel_title": "Robert Murray-Smith",
  "tags": [
    "Electroplating",
    "copper plating",
    "nickel plating",
    "organic electroplating",
    "zinc electroplating",
    "copperplating flowers",
    "copper plating leaves",
    "copper plating wood",
    "nickel plating leaves",
    "nickel plating flowers",
    "non metal electroplating",
    "electroplating",
    "leaves",
    "flowers",
    "electroplating booties",
    "electroplating momentos"
  ],
  "duration": "PT8M26S",
  "view_count": "66704",
  "like_count": "634",
  "comment_count": "102",
  "url": "https://www.youtube.com/watch?v=GoqchqZfMCc",
  "thumbnail": "https://i.ytimg.com/vi/GoqchqZfMCc/hqdefault.jpg"
}