{
  "video_id": "vYYgrJgjMv4",
  "title": "Copper Plating Keepsakes - A Rose",
  "description": "If you want to buy our conductive graphene ink you can get it from here\nhttps://secure.workingink.co.uk/product-category/working-ink-ink/\nIf you want the universal plating solution you can get it from here\nhttps://secure.workingink.co.uk/shop/working-ink-plating-and-deposition-solutions/universal-plating-solution/",
  "published_at": "2019-10-15T12:50:57Z",
  "channel_id": "UC4AkVj-qnJxNtKuz3rkq16A",
  "channel_title": "Robert Murray-Smith",
  "tags": [
    "graphene",
    "electroplating",
    "plating",
    "copper",
    "ink",
    "conductive'",
    "paint",
    "craft",
    "crafting",
    "jewellery",
    "jewelry",
    "fwg",
    "robert",
    "murray-smith"
  ],
  "duration": "PT1M42S",
  "view_count": "2807",
  "like_count": "107",
  "comment_count": "24",
  "url": "https://www.youtube.com/watch?v=vYYgrJgjMv4",
  "thumbnail": "https://i.ytimg.com/vi/vYYgrJgjMv4/hqdefault.jpg"
}