{
  "video_id": "guVsmBjCWa8",
  "title": "1685 DIY Easy Build Waste Oil Burner",
  "description": "Don't forget to check out our other channel found here https://www.youtube.com/channel/UC1E8OmOG17VckoPviOPmkMw\nIf you want to have a look at those special videos become a member and join by clicking this link https://www.youtube.com/channel/UC4AkVj-qnJxNtKuz3rkq16A/join\nDon't forget that you can buy my books and materials for your own experiments including our conductive inks at https://secure.workingink.co.uk/working-ink-shop/    - and for the many who have asked, yes, you can also donate to further our work, again through the shop.",
  "published_at": "2022-09-20T13:16:28Z",
  "channel_id": "UC4AkVj-qnJxNtKuz3rkq16A",
  "channel_title": "Robert Murray-Smith",
  "tags": [
    "diy",
    "how to",
    "oil",
    "waste",
    "burner",
    "robert",
    "feg",
    "tnt"
  ],
  "duration": "PT8M13S",
  "view_count": "93762",
  "like_count": "3268",
  "comment_count": "210",
  "url": "https://www.youtube.com/watch?v=guVsmBjCWa8",
  "thumbnail": "https://i.ytimg.com/vi/guVsmBjCWa8/hqdefault.jpg"
}